{
  "config": {
    "abort": {
      "already_configured": "[%key:common::config_flow::abort::already_configured_device%]",
      "already_in_progress": "[%key:common::config_flow::abort::already_in_progress%]"
    },
    "error": {
      "token_unauthorized": "The token is invalid or unauthorized."
    },
    "step": {
      "user": {
        "title": "Connect to ThinQ",
        "description": "Please enter a ThinQ [PAT(Personal Access Token)]({pat_url}) created with your LG ThinQ account.",
        "data": {
          "access_token": "Personal Access Token",
          "country": "Country"
        }
      }
    }
  },
  "entity": {
    "switch": {
      "operation_power": {
        "name": "Power"
      }
    },
    "binary_sensor": {
      "eco_friendly_mode": {
        "name": "Eco friendly"
      },
      "power_save_enabled": {
        "name": "Power saving mode"
      },
      "remote_control_enabled": {
        "name": "Remote start"
      },
      "remote_control_enabled_for_location": {
        "name": "{location} remote start"
      },
      "rinse_refill": {
        "name": "Rinse refill needed"
      },
      "sabbath_mode": {
        "name": "Sabbath"
      }
    },
    "sensor": {
      "error": {
        "name": "Error"
      },
      "current_temperature": {
        "name": "Current temperature"
      },
      "temperature": {
        "name": "Temperature"
      },
      "monitoring_enabled": {
        "name": "Air quality sensor"
      },
      "growth_mode": {
        "name": "Mode"
      },
      "growth_mode_for_location": {
        "name": "{location} mode"
      },
      "wind_volume": {
        "name": "Wind speed"
      },
      "wind_volume_for_location": {
        "name": "{location} wind speed"
      },
      "day_target_temperature": {
        "name": "Day growth temperature"
      },
      "day_target_temperature_for_location": {
        "name": "{location} day growth temperature"
      },
      "night_target_temperature": {
        "name": "Night growth temperature"
      },
      "night_target_temperature_for_location": {
        "name": "{location} night growth temperature"
      },
      "temperature_state": {
        "name": "Temperature"
      },
      "temperature_state_for_location": {
        "name": "{location} temperature"
      },
      "current_state": {
        "name": "Current status"
      },
      "current_state_for_location": {
        "name": "{location} current status"
      },
      "fresh_air_filter": {
        "name": "Fresh air filter"
      },
      "used_time": {
        "name": "Water filter used"
      },
      "current_job_mode": {
        "name": "Operating mode"
      },
      "current_job_mode_stick_cleaner": {
        "name": "Operating mode"
      },
      "personalization_mode": {
        "name": "Personal mode"
      },
      "cock_state": {
        "name": "UVnano"
      },
      "sterilizing_state": {
        "name": "High-temp sterilization"
      },
      "water_type": {
        "name": "Type"
      },
      "target_temperature": {
        "name": "Temperature"
      },
      "target_temperature_for_location": {
        "name": "{location} temperature"
      },
      "one_touch_filter": {
        "name": "Fresh air filter"
      }
    }
  }
}
